{
  "channels": {
    "ask": "",
    "blogAnnouncements": "",
    "earthTemple": "",
    "faq": "",
    "general": "",
    "modRequests": "",
    "transfer": ""
  },
  "emoji": {
    "messageContextMenu": {
      "bookmark": "🔖",
      "kesterBomb": "💣",
      "pin": "📌",
      "spoiler": "🤫"
    },
    "upDawn": "⬆",
    "unDawn": "↩"
  },
  "guilds": {
    "PrimaryServer": "",
    "ClimbersCourt": "",
    "TestServer": ""
  },
  "roles": {
    "BotMaster": "",
    "Admin": "",
    "SoaringWings": "",
    "Whisper": "",
    "WorldMaker": "",
    "Updates": {
      "BotUpdates": "",
      "MetaUpdates": "",
      "TTRPGUpdates": "",
      "BookUpdates": "",
      "BlogUpdates": "",
      "AllUpdates": "",
      "RoleplayingUpdates": ""
    }
  }
}